MANIFEST.in
pyproject.toml
setup.cfg
setup.py
sarus_data_spec/__init__.py
sarus_data_spec/attribute.py
sarus_data_spec/base.py
sarus_data_spec/bounds.py
sarus_data_spec/constants.py
sarus_data_spec/dataset.py
sarus_data_spec/deprecation.py
sarus_data_spec/factory.py
sarus_data_spec/json_serialisation.py
sarus_data_spec/marginals.py
sarus_data_spec/multiplicity.py
sarus_data_spec/path.py
sarus_data_spec/predicate.py
sarus_data_spec/py.typed
sarus_data_spec/scalar.py
sarus_data_spec/schema.py
sarus_data_spec/size.py
sarus_data_spec/statistics.py
sarus_data_spec/status.py
sarus_data_spec/transform.py
sarus_data_spec/type.py
sarus_data_spec/typing.py
sarus_data_spec/variant_constraint.py
sarus_data_spec/arrow/__init__.py
sarus_data_spec/arrow/admin_utils.py
sarus_data_spec/arrow/array.py
sarus_data_spec/arrow/conversion.py
sarus_data_spec/arrow/pandas_utils.py
sarus_data_spec/arrow/schema.py
sarus_data_spec/arrow/type.py
sarus_data_spec/context/__init__.py
sarus_data_spec/context/public.py
sarus_data_spec/context/state.py
sarus_data_spec/context/typing.py
sarus_data_spec/dataspec_rewriter/__init__.py
sarus_data_spec/dataspec_rewriter/base.py
sarus_data_spec/dataspec_rewriter/graph_query_builder_utils.py
sarus_data_spec/dataspec_rewriter/recursive_rewriter.py
sarus_data_spec/dataspec_rewriter/simple_rules.py
sarus_data_spec/dataspec_rewriter/typing.py
sarus_data_spec/dataspec_rewriter/utils.py
sarus_data_spec/dataspec_validator/__init__.py
sarus_data_spec/dataspec_validator/base.py
sarus_data_spec/dataspec_validator/caching_utils.py
sarus_data_spec/dataspec_validator/parameter_kind.py
sarus_data_spec/dataspec_validator/privacy_limit.py
sarus_data_spec/dataspec_validator/recursive_validator.py
sarus_data_spec/dataspec_validator/signature.py
sarus_data_spec/dataspec_validator/simple_rules.py
sarus_data_spec/dataspec_validator/typing.py
sarus_data_spec/manager/__init__.py
sarus_data_spec/manager/async_utils.py
sarus_data_spec/manager/base.py
sarus_data_spec_public.egg-info/PKG-INFO
sarus_data_spec_public.egg-info/SOURCES.txt
sarus_data_spec_public.egg-info/dependency_links.txt
sarus_data_spec_public.egg-info/not-zip-safe
sarus_data_spec_public.egg-info/requires.txt
sarus_data_spec_public.egg-info/top_level.txt