Metadata-Version: 2.1
Name: sarus_data_spec_public
Version: 4.5.1
Summary: A library to manage Sarus datasets
Home-page: 
Download-URL: 
Author: Sarus Technologies
Author-email: 
License: Apache License 2.0
Classifier: Programming Language :: Python :: 3
Classifier: Programming Language :: Python :: 3.8
Classifier: Programming Language :: Python :: 3.9
Provides: sarus_data_spec_public
Requires-Python: >=3.8
Requires-Dist: protobuf<4.0,>=3.0
Requires-Dist: numpy>=1.20.0
Requires-Dist: pyarrow~=15.0.0
Requires-Dist: fsspec[gcs,http]>=2021.0
Requires-Dist: tqdm>=4.0
Requires-Dist: pandas~=1.4.0
Requires-Dist: pyyaml>=5.4.1
Requires-Dist: scipy>=1.9.0
